{
  "server": "34.136.244.16",
  "browserPort": "7474",
  "trustAllCertificatesVariable": "",
  "databaseName": "twitter300m",
  "maxConnectionLifetime": "",
  "routingVariable": "",
  "manualUrls": [],
  "routingPolicy": "",
  "boltPort": "7687",
  "usingEncryption": false,
  "trustAllCertificates": false,
  "routing": true,
  "password": "Encrypted 2be98afc86aa7f2e4cb2db931ca86fcc8",
  "usingEncryptionVariable": "",
  "version4": true,
  "maxTransactionRetryTime": "",
  "name": "neo4j_graph",
  "maxConnectionPoolSize": "",
  "connectionLivenessCheckTimeout": "",
  "connectionTimeout": "",
  "connectionAcquisitionTimeout": "",
  "username": "neo4j",
  "version4Variable": ""
}